ncdtecbook/__init__.py
ncdtecbook/example.py
ncdtecbook/isec/__init__.py
ncdtecbook/isec/rc4.py
ncdtecbook/it/__init__.py
ncdtecbook/it/graph.py
ncdtecbook-0.0.1.6.dist-info/METADATA
ncdtecbook-0.0.1.6.dist-info/WHEEL
ncdtecbook-0.0.1.6.dist-info/licenses/LICENSE
ncdtecbook-0.0.1.6.dist-info/RECORD
