Metadata-Version: 2.3
Name: ncdtecbook
Version: 0.0.1.6
Summary: NCD-TEC Book examples
Project-URL: Homepage, https://github.com/suhelhammoud/ncd-tec-book
Project-URL: Issues, https://github.com/suhelhammoud/ncd-tec-book/issues
Author-email: Suhel Hammoud <suhel.hammoud@gmail.com>
License-File: LICENSE
Classifier: License :: OSI Approved :: MIT License
Classifier: Operating System :: OS Independent
Classifier: Programming Language :: Python :: 3
Requires-Python: >=3.8
